causalimpact/__init__.py
causalimpact/analysis.py
causalimpact/inferences.py
causalimpact/misc.py
causalimpact/model.py
causalimpact-0.2.6.dist-info/METADATA
causalimpact-0.2.6.dist-info/WHEEL
causalimpact-0.2.6.dist-info/top_level.txt
causalimpact-0.2.6.dist-info/RECORD
