Metadata-Version: 2.1
Name: causalimpact
Version: 0.2.6
Summary: Python Package for causal inference using Bayesian structural time-series models
Home-page: https://github.com/jamalsenouci/causalimpact/
Author: Jamal Senouci
Author-email: jamalsenouci@gmail.com
License: MIT
Project-URL: Documentation, https://nbviewer.org/github/jamalsenouci/causalimpact/blob/master/GettingStarted.ipynb
Project-URL: Source, https://github.com/jamalsenouci/causalimpact/
Project-URL: Changelog, https://github.com/jamalsenouci/causalimpact/CHANGELOG.md
Project-URL: Download, https://pypi.python.org/pypi/causalimpact/
Platform: any
Classifier: Development Status :: 4 - Beta
Classifier: Programming Language :: Python
Requires-Python: >=2.6
Requires-Dist: pandas
Requires-Dist: numpy
Requires-Dist: statsmodels
Requires-Dist: matplotlib
Requires-Dist: pymc
Requires-Dist: pytensor
Requires-Dist: importlib-metadata ; python_version < "3.8"
Provides-Extra: testing
Requires-Dist: setuptools ; extra == 'testing'
Requires-Dist: pytest ; extra == 'testing'
Requires-Dist: pytest-cov ; extra == 'testing'
